file_collection_hash/__init__.py
file_collection_hash/__main__.py
file_collection_hash/fc_hash.py
file_collection_hash/py.typed
file_collection_hash/version.py
file_collection_hash-1.0.0.dist-info/entry_points.txt
file_collection_hash-1.0.0.dist-info/LICENSE
file_collection_hash-1.0.0.dist-info/WHEEL
file_collection_hash-1.0.0.dist-info/METADATA
file_collection_hash-1.0.0.dist-info/RECORD
