Metadata-Version: 2.1
Name: file-collection-hash
Version: 1.0.0
Summary: Stable, fast hash of collection of content of files and directories, optionally including permissions, dates, etc.
Home-page: https://github.com/sammck/file-collection
License: MIT
Keywords: hash,compare,file,directory,tar,sha,md5,tarball,archive,zip,gzip
Author: Sam McKelvie
Author-email: dev@mckelvie.org
Requires-Python: >=3.7,<4.0
Classifier: License :: OSI Approved :: MIT License
Classifier: Programming Language :: Python :: 3
Classifier: Programming Language :: Python :: 3.10
Classifier: Programming Language :: Python :: 3.7
Classifier: Programming Language :: Python :: 3.8
Classifier: Programming Language :: Python :: 3.9
Project-URL: Repository, https://github.com/sammck/file-collection.git
